jsonschema_explorer/__init__.py
jsonschema_explorer/core.py
jsonschema_explorer-0.1.1.dist-info/licenses/LICENSE
jsonschema_explorer-0.1.1.dist-info/METADATA
jsonschema_explorer-0.1.1.dist-info/WHEEL
jsonschema_explorer-0.1.1.dist-info/top_level.txt
jsonschema_explorer-0.1.1.dist-info/RECORD
