Metadata-Version: 2.4
Name: jsonschema_explorer
Version: 0.1.1
Summary: A tool to parse JSON and extract schema
Home-page: https://github.com/s-farrant/jsonschema_explorer
Author: Sam Farrant
Author-email: samuel.farrant@gmail.com
License: MIT
Requires-Python: >=3.6
License-File: LICENSE
Dynamic: author
Dynamic: author-email
Dynamic: home-page
Dynamic: license
Dynamic: license-file
Dynamic: requires-python
Dynamic: summary
